CTkTable/__init__.py
CTkTable/ctktable.py
CTkTable-1.0.dist-info/LICENSE
CTkTable-1.0.dist-info/METADATA
CTkTable-1.0.dist-info/WHEEL
CTkTable-1.0.dist-info/dependency_links.txt
CTkTable-1.0.dist-info/top_level.txt
CTkTable-1.0.dist-info/RECORD
