Metadata-Version: 2.1
Name: CTkTable
Version: 1.0
Summary: Customtkinter Table widget
Home-page: https://github.com/Akascape/CTkTable
Author: Akash Bora
License: MIT
Keywords: customtkinter,tkinter,table-widget,table,ctktable,tabular-data,customtkinter-table
Classifier: License :: OSI Approved :: MIT License 
Classifier: Programming Language :: Python :: 3
Classifier: Operating System :: OS Independent
Requires-Python: >=3.6
License-File: LICENSE
Requires-Dist: customtkinter
